ehdg_tools/__init__.py
ehdg_tools/ehdg_buffers.py
ehdg_tools/ehdg_functions.py
ehdg_tools/ehdg_okn_checker.py
ehdg_tools/ehdg_plotter.py
ehdg_tools/ehdg_updater.py
ehdg_tools/pupil_lab_functions.py
ehdg_tools-4.6.3.dist-info/licenses/LICENSE
ehdg_tools-4.6.3.dist-info/METADATA
ehdg_tools-4.6.3.dist-info/WHEEL
ehdg_tools-4.6.3.dist-info/top_level.txt
ehdg_tools-4.6.3.dist-info/RECORD
