Metadata-Version: 2.4
Name: ehdg_tools
Version: 4.6.3
Summary: Python library useful tools for ABI Eye Health Diagnostic Group
Author-email: Zaw Lin Tun <zawlintun1511@gmail.com>
Project-URL: Homepage, https://github.com/ZawLinTun16925410/ehdg_tools
Project-URL: Bug Tracker, https://github.com/ZawLinTun16925410/ehdg_tools/issues
Classifier: Programming Language :: Python :: 3
Classifier: License :: OSI Approved :: Apache Software License
Classifier: Operating System :: OS Independent
License-File: LICENSE
Requires-Dist: setuptools>=61.0
Requires-Dist: numpy>=1.26.1
Requires-Dist: commentjson
Requires-Dist: scipy
Requires-Dist: matplotlib
Requires-Dist: opencv-python>=4.10.0.84
Dynamic: license-file
